Workbook

Sheet Assumptions
A1: Lucidity Cowork — Infrastructure Cost Model
A3: ASSUMPTIONS | B3: MVP (Month 1-3) | C3: Growth (Month 4-9) | D3: Scale (Month 10-18) | E3: Notes
A4: USER ASSUMPTIONS
A5: Monthly Active Users (MAU) | B5: 20 | C5: 200 | D5: 1000 | E5: Paying + free tier users
A6: Concurrent Users (peak) | B6: 5 | C6: 40 | D6: 150 | E6: ~20-25% of MAU at peak
A7: Avg Sessions per User per Month | B7: 15 | C7: 12 | D7: 10 | E7: Power users skew higher
A8: Avg Session Duration (minutes) | B8: 30 | C8: 25 | D8: 20 | E8: Each active build/edit session
A9: Total Sandbox Hours / Month | B9: =B5*B7*B8/60 -> 150 | C9: =C5*C7*C8/60 -> 1000 | D9: =D5*D7*D8/60 -> 3333.3333 | E9: MAU × sessions × duration
A11: LLM USAGE PER SESSION
A12: Canvas Agent Calls per Session | B12: 8 | C12: 8 | D12: 8 | E12: Understanding, threading, annotations
A13: Executor Agent Calls per Session | B13: 12 | C13: 12 | D13: 12 | E13: Code gen, file writes, commands
A14: Avg Input Tokens per Call | B14: 4000 | C14: 4000 | D14: 4000 | E14: System prompt + context + user msg
A15: Avg Output Tokens per Call | B15: 2000 | C15: 2000 | D15: 2000 | E15: Generated code, explanations
A16: Total Sessions / Month | B16: =B5*B7 -> 300 | C16: =C5*C7 -> 2400 | D16: =D5*D7 -> 10000 | E16: MAU × sessions/user
A18: REVENUE ASSUMPTIONS
A19: Paying User % | B19: 0.1 | C19: 0.15 | D19: 0.2 | E19: Free-to-paid conversion
A20: Monthly Price per Paying User ($) | B20: 25 | C20: 25 | D20: 25 | E20: Comparable to Bolt/Lovable Starter
A21: Monthly Revenue ($) | B21: =B5*B19*B20 -> 50 | C21: =C5*C19*C20 -> 750 | D21: =D5*D19*D20 -> 5000 | E21: MAU × pay% × price

Sheet Cost Breakdown
A1: Monthly Infrastructure Cost Breakdown
A2: Component | B2: Unit Cost | C2: MVP | D2: Growth | E2: Scale | F2: Pricing Source / Notes
A3: 1. SANDBOX INFRASTRUCTURE (E2B)
A4: E2B Pro Base Fee | B4: $150/month | C4: 150 | D4: 150 | E4: 150 | F4: E2B Pro plan, 24hr sessions, 100 concurrent
A5: Sandbox Compute (1 vCPU / 2GB) | B5: $0.05/hr | C5: =Assumptions!B9*0.05 -> 7.5 | D5: =Assumptions!C9*0.05 -> 50 | E5: =Assumptions!D9*0.05 -> 166.66667 | F5: ~$0.05/hr for 1vCPU+2GB (E2B Pro)
A6: Subtotal: Sandbox | C6: =SUM(C4:C5) -> 157.5 | D6: =SUM(D4:D5) -> 200 | E6: =SUM(E4:E5) -> 316.66667
A8: 2. LLM API COSTS
A9: Canvas Agent (Gemini 2.5 Flash) - Input | B9: $0.50/1M tok | C9: =Assumptions!B16*Assumptions!B12*Assumptions!B14/1000000*0.5 -> 4.8 | D9: =Assumptions!C16*Assumptions!C12*Assumptions!C14/1000000*0.5 -> 38.4 | E9: =Assumptions!D16*Assumptions!D12*Assumptions!D14/1000000*0.5 -> 160 | F9: Gemini 2.5 Flash: $0.50/1M input
A10: Canvas Agent (Gemini 2.5 Flash) - Output | B10: $2.50/1M tok | C10: =Assumptions!B16*Assumptions!B12*Assumptions!B15/1000000*2.5 -> 12 | D10: =Assumptions!C16*Assumptions!C12*Assumptions!C15/1000000*2.5 -> 96 | E10: =Assumptions!D16*Assumptions!D12*Assumptions!D15/1000000*2.5 -> 400 | F10: Gemini 2.5 Flash: $2.50/1M output (thinking)
A11: Executor Agent (Claude Sonnet 4.5) - Input | B11: $3/1M tok | C11: =Assumptions!B16*Assumptions!B13*Assumptions!B14/1000000*3 -> 43.2 | D11: =Assumptions!C16*Assumptions!C13*Assumptions!C14/1000000*3 -> 345.6 | E11: =Assumptions!D16*Assumptions!D13*Assumptions!D14/1000000*3 -> 1440 | F11: Claude Sonnet 4.5: $3/1M input
A12: Executor Agent (Claude Sonnet 4.5) - Output | B12: $15/1M tok | C12: =Assumptions!B16*Assumptions!B13*Assumptions!B15/1000000*15 -> 108 | D12: =Assumptions!C16*Assumptions!C13*Assumptions!C15/1000000*15 -> 864 | E12: =Assumptions!D16*Assumptions!D13*Assumptions!D15/1000000*15 -> 3600 | F12: Claude Sonnet 4.5: $15/1M output
A13: Embeddings (text-embedding-3-small) | B13: $0.02/1M tok | C13: =Assumptions!B16*50000/1000000*0.02 -> 0.3 | D13: =Assumptions!C16*50000/1000000*0.02 -> 2.4 | E13: =Assumptions!D16*50000/1000000*0.02 -> 10 | F13: OpenAI embedding: $0.02/1M, ~50K tok/session
A14: Subtotal: LLM APIs | C14: =SUM(C9:C13) -> 168.3 | D14: =SUM(D9:D13) -> 1346.4 | E14: =SUM(E9:E13) -> 5610
A16: 3. DATABASE & STORAGE
A17: Supabase (Postgres + pgvector) | B17: $0-25/month | C17: 0 | D17: 25 | E17: 25 | F17: Free tier → Pro $25/mo (8GB DB, 100K MAU)
A18: Redis (Upstash serverless) | B18: $0-10/month | C18: 0 | D18: 0 | E18: 10 | F18: Caching, session state. Free 10K cmds/day
A19: Subtotal: Database | C19: =SUM(C17:C18) -> 0 | D19: =SUM(D17:D18) -> 25 | E19: =SUM(E17:E18) -> 35
A21: 4. FRONTEND HOSTING & INFRA
A22: Vercel (Next.js frontend) | B22: $0-20/month | C22: 0 | D22: 20 | E22: 20 | F22: Hobby free → Pro $20/mo/member
A23: Backend Server (Railway / Fly.io) | B23: $5-25/month | C23: 5 | D23: 15 | E23: 50 | F23: LangGraph orchestration server, WebSockets
A24: Domain + DNS (Cloudflare) | B24: $10-15/year | C24: 1 | D24: 1 | E24: 1 | F24: ~$12/year amortized
A25: Subtotal: Hosting | C25: =SUM(C22:C24) -> 6 | D25: =SUM(D22:D24) -> 36 | E25: =SUM(E22:E24) -> 71
A27: 5. AUTH, MONITORING & MISC
A28: Auth (Supabase Auth / Clerk) | B28: $0/month | C28: 0 | D28: 0 | E28: 0 | F28: Bundled with Supabase, or Clerk free tier
A29: Error Tracking (Sentry) | B29: $0/month | C29: 0 | D29: 0 | E29: 29 | F29: Free tier → Team $29/mo at scale
A30: Analytics (PostHog / Plausible) | B30: $0/month | C30: 0 | D30: 0 | E30: 0 | F30: PostHog free tier: 1M events/mo
A31: Subtotal: Auth & Misc | C31: =SUM(C28:C30) -> 0 | D31: =SUM(D28:D30) -> 0 | E31: =SUM(E28:E30) -> 29
A33: TOTAL MONTHLY INFRASTRUCTURE COST | C33: =C6+C14+C19+C25+C31 -> 331.8 | D33: =D6+D14+D19+D25+D31 -> 1607.4 | E33: =E6+E14+E19+E25+E31 -> 6061.6667
A34: Monthly Revenue (from Assumptions) | C34: =Assumptions!B21 -> 50 | D34: =Assumptions!C21 -> 750 | E34: =Assumptions!D21 -> 5000
A35: Net Margin (Revenue - Cost) | C35: =C34-C33 -> -281.8 | D35: =D34-D33 -> -857.4 | E35: =E34-E33 -> -1061.6667
A36: Gross Margin % | C36: =IF(C34=0,"N/A",C35/C34) -> -5.636 | D36: =IF(D34=0,"N/A",D35/D34) -> -1.1432 | E36: =IF(E34=0,"N/A",E35/E34) -> -0.21233333
A38: COST PER USER METRICS
A39: Total Cost per MAU | C39: =C33/Assumptions!B5 -> 16.59 | D39: =D33/Assumptions!C5 -> 8.037 | E39: =E33/Assumptions!D5 -> 6.0616667
A40: LLM Cost per Session | C40: =C14/Assumptions!B16 -> 0.561 | D40: =D14/Assumptions!C16 -> 0.561 | E40: =E14/Assumptions!D16 -> 0.561
A41: Sandbox Cost per Session | C41: =C6/Assumptions!B16 -> 0.525 | D41: =D6/Assumptions!C16 -> 0.083333333 | E41: =E6/Assumptions!D16 -> 0.031666667
A42: Revenue per Paying User - Cost per MAU | C42: =Assumptions!B20-C39 -> 8.41 | D42: =Assumptions!C20-D39 -> 16.963 | E42: =Assumptions!D20-E39 -> 18.938333 | F42: Headroom per paying user after costs

Sheet Cost Distribution
A1: Cost Distribution by Category
A2: Category | B2: MVP | C2: Growth | D2: Scale
A3: Sandbox (E2B) | B3: ='Cost Breakdown'!C6 -> 157.5 | C3: ='Cost Breakdown'!D6 -> 200 | D3: ='Cost Breakdown'!E6 -> 316.66667
A4: LLM APIs | B4: ='Cost Breakdown'!C14 -> 168.3 | C4: ='Cost Breakdown'!D14 -> 1346.4 | D4: ='Cost Breakdown'!E14 -> 5610
A5: Database | B5: ='Cost Breakdown'!C19 -> 0 | C5: ='Cost Breakdown'!D19 -> 25 | D5: ='Cost Breakdown'!E19 -> 35
A6: Hosting | B6: ='Cost Breakdown'!C25 -> 6 | C6: ='Cost Breakdown'!D25 -> 36 | D6: ='Cost Breakdown'!E25 -> 71
A7: Auth & Misc | B7: ='Cost Breakdown'!C31 -> 0 | C7: ='Cost Breakdown'!D31 -> 0 | D7: ='Cost Breakdown'!E31 -> 29
A8: Total | B8: =SUM(B3:B7) -> 331.8 | C8: =SUM(C3:C7) -> 1607.4 | D8: =SUM(D3:D7) -> 6061.6667
A10: % of Total | B10: MVP | C10: Growth | D10: Scale
A11: Sandbox (E2B) | B11: =IF(B8=0,0,B3/B8) -> 0.47468354 | C11: =IF(C8=0,0,C3/C8) -> 0.12442454 | D11: =IF(D8=0,0,D3/D8) -> 0.052240858
A12: LLM APIs | B12: =IF(B8=0,0,B4/B8) -> 0.50723327 | C12: =IF(C8=0,0,C4/C8) -> 0.83762598 | D12: =IF(D8=0,0,D4/D8) -> 0.92548804
A13: Database | B13: =IF(B8=0,0,B5/B8) -> 0 | C13: =IF(C8=0,0,C5/C8) -> 0.015553067 | D13: =IF(D8=0,0,D5/D8) -> 0.0057739896
A14: Hosting | B14: =IF(B8=0,0,B6/B8) -> 0.018083183 | C14: =IF(C8=0,0,C6/C8) -> 0.022396417 | D14: =IF(D8=0,0,D6/D8) -> 0.01171295
A15: Auth & Misc | B15: =IF(B8=0,0,B7/B8) -> 0 | C15: =IF(C8=0,0,C7/C8) -> 0 | D15: =IF(D8=0,0,D7/D8) -> 0.0047841628

Sheet Pricing Reference
A1: Vendor Pricing Reference (Feb 2026)
A2: Service / Model | B2: Input Price | C2: Output Price | D2: Notes
A3: LLM APIS
A4: Claude Opus 4.5 | B4: $5.00 / 1M tok | C4: $25.00 / 1M tok | D4: Most capable. 67% cheaper than Opus 4.1
A5: Claude Sonnet 4.5 | B5: $3.00 / 1M tok | C5: $15.00 / 1M tok | D5: Best balance for production. 1M context
A6: Claude Haiku 4.5 | B6: $1.00 / 1M tok | C6: $5.00 / 1M tok | D6: Fastest. Good for routing/classification
A7: Gemini 2.5 Pro | B7: $1.25 / 1M tok | C7: $10.00 / 1M tok | D7: ≤200K ctx. Doubles >200K tokens
A8: Gemini 2.5 Flash | B8: $0.30 / 1M tok | C8: $2.50 / 1M tok | D8: With thinking. $0.15/$0.60 without
A9: Gemini 3 Flash | B9: $0.50 / 1M tok | C9: $3.00 / 1M tok | D9: Frontier at Flash pricing. Dec 2025
A10: Gemini 3 Pro | B10: $2.00 / 1M tok | C10: $12.00 / 1M tok | D10: Preview. Best multimodal
A11: GPT-5 | B11: $1.25 / 1M tok | C11: $10.00 / 1M tok | D11: Most affordable flagship Jan 2026
A13: EMBEDDINGS
A14: text-embedding-3-small | B14: $0.02 / 1M tok | C14: N/A | D14: 1536 dims. Best cost/perf ratio
A15: text-embedding-3-large | B15: $0.13 / 1M tok | C15: N/A | D15: 3072 dims. Higher quality
A16: Gemini embedding | B16: Free (AI Studio) | C16: N/A | D16: Free tier available. $0.006/1M Vertex
A18: SANDBOX PROVIDERS
A19: E2B (Pro) | B19: $150/mo base | C19: $0.05/hr (1vCPU) | D19: Firecracker microVMs. 24hr sessions, 100 concurrent
A20: Daytona | B20: $200 free credits | C20: $0.067/hr (1vCPU) | D20: Sub-90ms cold start. Stateful persistence
A21: Novita Sandbox | B21: No base fee | C21: $0.035/hr (1vCPU) | D21: E2B-compatible API. 30% cheaper compute
A22: CodeSandbox | B22: Free (40hrs) | C22: $0.015/credit | D22: VM credit system. Pico VMs
A23: Vercel Sandbox | B23: Free (5 CPU-hrs) | C23: $0.128/CPU-hr | D23: Beta. 45min max runtime
A25: DATABASE / STORAGE
A26: Supabase Free | B26: $0/month | D26: 500MB DB, 50K MAU, pgvector included
A27: Supabase Pro | B27: $25/month | D27: 8GB DB, 100K MAU, daily backups
A28: Upstash Redis | B28: $0/month | D28: Free: 10K commands/day. Pay-as-you-go after
A30: HOSTING
A31: Vercel Hobby | B31: $0/month | D31: Non-commercial. 60s function timeout
A32: Vercel Pro | B32: $20/mo/member | D32: 1TB bandwidth, 5min functions, team features
A33: Railway | B33: $5/month | D33: Starter. $0.000463/min vCPU. Good for backends
A34: Fly.io | B34: $0/month | D34: Free tier: 3 shared VMs. Pay as you scale

Sheet Optimization Notes
A1: Cost Optimization Strategies
A2: Strategy | B2: Details | C2: Estimated Savings
A3: LLM COST REDUCTION
A4: Prompt Caching (Claude) | B4: Cache system prompts + knowledge context. 90% discount on cached input tokens ($0.30 vs $3/1M) | C4: 40-60% on LLM input
A5: Gemini Free Tier | B5: Use Google AI Studio free tier for canvas agent during MVP (1,500 RPD) | C5: 100% on canvas agent (MVP)
A6: Model Routing | B6: Use Haiku ($1/$5) for simple tasks, Sonnet for code gen. Route by complexity | C6: 30-50% on LLM overall
A7: Batch API (50% off) | B7: Non-urgent tasks (knowledge indexing, review) via Claude Batch API | C7: 50% on batch-eligible calls
A8: Shorter Prompts | B8: Optimize system prompts. Strip unnecessary context. Use XML tags for structure | C8: 10-20% across all LLM
A10: SANDBOX OPTIMIZATION
A11: Auto-Sleep Sandboxes | B11: Kill idle sandboxes after 5min inactivity instead of session timeout | C11: 40-60% on sandbox compute
A12: Shared Templates | B12: Pre-built sandbox templates (Next.js, Flask) avoid repeated npm installs | C12: Reduced session startup time
A13: Switch to Novita/Self-Host | B13: Novita: 30% cheaper than E2B. Self-hosted Firecracker at scale | C13: 30-70% on sandbox (at scale)
A15: INFRASTRUCTURE
A16: Supabase + pgvector | B16: Avoid separate vector DB (Pinecone $70/mo). Use pgvector in same Postgres | C16: $70+/mo saved
A17: Edge Caching | B17: Cache frequently accessed knowledge graph queries at CDN edge | C17: Reduced DB load + latency
A18: Free Tiers Stacking | B18: Supabase Free + Vercel Hobby + PostHog Free + Sentry Free | C18: $0 infra for MVP
